alexigna_python2025/__init__.py
alexigna_python2025/main.py
alexigna_python2025-0.1.0.dist-info/METADATA
alexigna_python2025-0.1.0.dist-info/WHEEL
alexigna_python2025-0.1.0.dist-info/RECORD
