Metadata-Version: 2.3
Name: alexigna-python2025
Version: 0.1.0
Summary: 
Author: alsigna
Author-email: ignatov.alx@gmail.com
Requires-Python: >=3.13
Classifier: Programming Language :: Python :: 3
Classifier: Programming Language :: Python :: 3.13
Requires-Dist: pyyaml (>=6.0.2,<7.0.0)
